jadbio/__init__.py
jadbio/client.py
jadbio-1.2.15.dist-info/LICENSE
jadbio-1.2.15.dist-info/METADATA
jadbio-1.2.15.dist-info/WHEEL
jadbio-1.2.15.dist-info/top_level.txt
jadbio-1.2.15.dist-info/RECORD
