Metadata-Version: 2.1
Name: jadbio
Version: 1.2.15
Summary: A python wrapper for the public JADBio REST API.
Home-page: https://github.com/JADBio/JADBioPythonClient
Author: JADBio
Author-email: support@jadbio.com
License: GPL3.0
Project-URL: Homepage, https://jadbio.com
Project-URL: Documentation, https://support.jadbio.com/pythonclient/1.2.15
Project-URL: Source code, https://github.com/JADBio/JADBioPythonClient
Keywords: jadbio automl machine-learning
Classifier: Development Status :: 5 - Production/Stable
Classifier: Intended Audience :: Developers
Classifier: Intended Audience :: Healthcare Industry
Classifier: Intended Audience :: Science/Research
Classifier: License :: OSI Approved :: GNU General Public License v3 (GPLv3)
Classifier: Operating System :: OS Independent
Classifier: Programming Language :: Python :: 3
Classifier: Topic :: Scientific/Engineering :: Artificial Intelligence
Classifier: Topic :: Scientific/Engineering :: Bio-Informatics
Requires-Python: >=3.0
License-File: LICENSE
Requires-Dist: requests-toolbelt >=0.9.1
Requires-Dist: requests >=2.25.0
Requires-Dist: sphinx >=4.4.0
Requires-Dist: sphinx-markdown-builder <0.6,>=0.5.5
Requires-Dist: toml >=0.10.0
